snipergw/__main__.py
snipergw/model.py
snipergw/paths.py
snipergw/plan.py
snipergw/run.py
snipergw/skymap.py
snipergw/submit/__init__.py
snipergw/submit/winter.py
snipergw/submit/ztf.py
snipergw-1.0.0.dist-info/LICENSE
snipergw-1.0.0.dist-info/METADATA
snipergw-1.0.0.dist-info/WHEEL
snipergw-1.0.0.dist-info/top_level.txt
snipergw-1.0.0.dist-info/RECORD
