Metadata-Version: 2.1
Name: snipergw
Version: 1.0.0
Author-email: Robert Stein <rdstein@caltech.edu>
License: MIT
Project-URL: Homepage, https://github.com/robertdstein/snipergw
Classifier: Programming Language :: Python :: 3
Classifier: Programming Language :: Python :: 3.10
Classifier: Programming Language :: Python :: 3.11
Classifier: Intended Audience :: Science/Research
Classifier: Intended Audience :: End Users/Desktop
Classifier: Intended Audience :: Developers
Classifier: Natural Language :: English
Classifier: Topic :: Scientific/Engineering
Classifier: Topic :: Scientific/Engineering :: Astronomy
Classifier: Topic :: Scientific/Engineering :: Physics
Classifier: Operating System :: POSIX
Classifier: Operating System :: Unix
Classifier: Operating System :: MacOS
Requires-Python: >=3.10
License-File: LICENSE
Requires-Dist: requests
Requires-Dist: backoff
Requires-Dist: ligo-gracedb
Requires-Dist: lxml
Requires-Dist: wget
Requires-Dist: astropy
Requires-Dist: numpy
Requires-Dist: gwemopt ==0.2.2
Requires-Dist: pandas
Requires-Dist: pydantic >=2.2.0
Requires-Dist: planobs
Requires-Dist: winterapi >=1.4.0
Provides-Extra: dev
Requires-Dist: black ==24.4.2 ; extra == 'dev'
Requires-Dist: isort ==5.13.2 ; extra == 'dev'
Requires-Dist: pylint ==3.2.2 ; extra == 'dev'
Requires-Dist: coveralls ; extra == 'dev'
